{
    "project": {
        "projectId": 4421,
        "title": "OLED Interactive Display Helmet",
        "primaryTaxonomyNodes": [
            {
                "taxonomyNodeId": 10698,
                "taxonomyRootId": 8816,
                "parentNodeId": 10693,
                "level": 3,
                "code": "TX06.3.5",
                "title": "Food Production, Processing, and Preservation",
                "definition": "Food production, processing, preservation technologies include both space and Earth technologies that safely produce and handle food to reduce up-mass and retain maximum nutritional value.",
                "exampleTechnologies": "Bioregenerative food system, vegetable production system, packaged food mass reduction, vegetable cleaning and safety verification, stabilized foods, low oxygen permeability barrier films, plants habitat",
                "hasChildren": false,
                "hasInteriorContent": true
            }
        ],
        "startYear": 2012,
        "startMonth": 10,
        "endYear": 2014,
        "endMonth": 9,
        "statusDescription": "Completed",
        "programDirectors": [
            {
                "contactId": 335305,
                "firstName": "Michael",
                "lastName": "Lapointe",
                "fullName": "Michael R Lapointe",
                "fullNameInverted": "Lapointe, Michael R",
                "middleInitial": "R",
                "primaryEmail": "michael.r.lapointe@nasa.gov",
                "publicEmail": true,
                "nacontact": false
            }
        ],
        "programExecutives": [
            {
                "contactId": 392233,
                "firstName": "Richard",
                "lastName": "Howard",
                "fullName": "Richard W Howard",
                "fullNameInverted": "Howard, Richard W",
                "middleInitial": "W",
                "primaryEmail": "richard.w.howard@nasa.gov",
                "publicEmail": true,
                "nacontact": false
            }
        ],
        "libraryItems": [],
        "transitions": [],
        "responsibleMd": {
            "acronym": "STMD",
            "canUserEdit": false,
            "city": "",
            "external": false,
            "linkCount": 0,
            "organizationId": 4875,
            "organizationName": "Space Technology Mission Directorate",
            "organizationType": "NASA_Mission_Directorate",
            "naorganization": false,
            "organizationTypePretty": "NASA Mission Directorate"
        },
        "program": {
            "acronym": "CIF",
            "active": true,
            "description": "<p>Through the Center Innovation Fund, the Space Technology Mission Directorate allocates a small portion of the NASA workforce and procurement budget to internal research and development to feed early stage innovation in technology and exploration.&nbsp;Activities with in the Center Innovation Fund are proposed and led by NASA scientists and engineers. &nbsp;These activities and creative initiatives pursue emerging technologies that leverage talent and capabilities at the NASA Centers.</p><p>&nbsp;</p><p>&nbsp;</p>",
            "programId": 64,
            "responsibleMd": {
                "acronym": "STMD",
                "canUserEdit": false,
                "city": "",
                "external": false,
                "linkCount": 0,
                "organizationId": 4875,
                "organizationName": "Space Technology Mission Directorate",
                "organizationType": "NASA_Mission_Directorate",
                "naorganization": false,
                "organizationTypePretty": "NASA Mission Directorate"
            },
            "responsibleMdId": 4875,
            "stockImageFileId": 36643,
            "title": "Center Innovation Fund"
        },
        "statesWithWork": [
            {
                "abbreviation": "TX",
                "country": {
                    "abbreviation": "US",
                    "countryId": 236,
                    "name": "United States"
                },
                "countryId": 236,
                "name": "Texas",
                "stateTerritoryId": 29
            }
        ],
        "lastUpdated": "2018-10-10",
        "releaseStatusString": "Released",
        "endDateString": "Sep 2014",
        "startDateString": "Oct 2012"
    }
}